flask_bs
