Metadata-Version: 1.0
Name: Flask-BS
Version: 0.5.4
Summary: Another flask extension that provides Bootstrap CSS, JS and HTML5 boilerplate.
Home-page: https://github.com/bschumacher/Flask-BS
Author: Bill Schumacher
Author-email: bill@servernet.co
License: LGPLv3
Keywords: flask bootstrap html5 boilerplate
Platform: UNKNOWN
